qrkey/__about__.py
qrkey/__init__.py
qrkey/api.py
qrkey/crypto.py
qrkey/models.py
qrkey/mqtt.py
qrkey/settings.py
qrkey/tests/__init__.py
qrkey/tests/test_api.py
qrkey/tests/test_crypto.py
qrkey/ui/.env
qrkey/ui/.env.test
qrkey/ui/.gitignore
qrkey/ui/package-lock.json
qrkey/ui/package.json
qrkey/ui/build/asset-manifest.json
qrkey/ui/build/index.html
qrkey/ui/build/manifest.json
qrkey/ui/build/robots.txt
qrkey/ui/build/static/css/main.3135d883.css
qrkey/ui/build/static/css/main.3135d883.css.map
qrkey/ui/build/static/js/main.521f7acd.js
qrkey/ui/build/static/js/main.521f7acd.js.LICENSE.txt
qrkey/ui/build/static/js/main.521f7acd.js.map
qrkey/ui/build/static/media/bootstrap-icons.39795c0b4513de014cf8.woff
qrkey/ui/build/static/media/bootstrap-icons.b7bcc075b395c14ce8c2.woff2
qrkey/ui/public/index.html
qrkey/ui/public/manifest.json
qrkey/ui/public/robots.txt
qrkey/ui/src/PinCode.css
qrkey/ui/src/PinCode.js
qrkey/ui/src/PinCode.test.js
qrkey/ui/src/index.css
qrkey/ui/src/index.js
qrkey/ui/src/setupTests.js
utils/hooks/sdist.py
utils/hooks/wheel.py
qrkey-0.10.0.dist-info/METADATA
qrkey-0.10.0.dist-info/WHEEL
qrkey-0.10.0.dist-info/licenses/AUTHORS
qrkey-0.10.0.dist-info/licenses/LICENSE.txt
qrkey-0.10.0.dist-info/RECORD
